<?xml version="1.0"?><Report><ReportQuery><Format><ReportTitle>Surat IMB</ReportTitle><ReportDescription>Coba surat IMB</ReportDescription><PageSize>.DEFAULT</PageSize><PageOrientation>.DEFAULT</PageOrientation><TopMargin></TopMargin><BottomMargin></BottomMargin><RightMargin></RightMargin><LeftMargin></LeftMargin><pdfFont></pdfFont><pdfFontSize></pdfFontSize><PreExecuteCode>NONE</PreExecuteCode><formBetweenRows>solidline</formBetweenRows><gridDisplay>.DEFAULT</gridDisplay><gridSortable>.DEFAULT</gridSortable><gridSearchable>.DEFAULT</gridSearchable><gridPageable>.DEFAULT</gridPageable><gridPageSize>.DEFAULT</gridPageSize></Format><Datasource><SourceType>database</SourceType><SourceConnection><DatabaseType>mysql</DatabaseType><DatabaseName></DatabaseName><HostName></HostName><ServiceName></ServiceName><UserName></UserName><Password></Password></SourceConnection></Datasource><EntryForm><Query><TableSql></TableSql><WhereSql></WhereSql><GroupSql></GroupSql><RowSelection>all</RowSelection><SQL><QuerySql></QuerySql><SQLRaw>SELECT no_ktp, nama, lahir_tempat, lahir_tanggal, pekerjaan, alamat
FROM  pengaju
WHERE no_ktp = 2147483641</SQLRaw></SQL><QueryColumns><QueryColumn><Name>no_ktp</Name><TableName></TableName><ColumnName>no_ktp</ColumnName><ColumnType>char</ColumnType><ColumnLength>30</ColumnLength><Format><column_display>hide</column_display><content_type>plain</content_type><ColumnStartPDF></ColumnStartPDF><justify>left</justify><ColumnWidthPDF></ColumnWidthPDF><ColumnWidthHTML></ColumnWidthHTML><column_title></column_title><tooltip></tooltip><group_header_label></group_header_label><group_header_label_xpos></group_header_label_xpos><group_header_data_xpos></group_header_data_xpos><group_trailer_label></group_trailer_label></Format></QueryColumn><QueryColumn><Name>nama</Name><TableName></TableName><ColumnName>nama</ColumnName><ColumnType>char</ColumnType><ColumnLength>30</ColumnLength><Format><column_display>hide</column_display><content_type>plain</content_type><ColumnStartPDF></ColumnStartPDF><justify>left</justify><ColumnWidthPDF></ColumnWidthPDF><ColumnWidthHTML></ColumnWidthHTML><column_title></column_title><tooltip></tooltip><group_header_label></group_header_label><group_header_label_xpos></group_header_label_xpos><group_header_data_xpos></group_header_data_xpos><group_trailer_label></group_trailer_label></Format></QueryColumn><QueryColumn><Name>lahir_tempat</Name><TableName></TableName><ColumnName>lahir_tempat</ColumnName><ColumnType>char</ColumnType><ColumnLength>30</ColumnLength><Format><column_display>hide</column_display><content_type>plain</content_type><ColumnStartPDF></ColumnStartPDF><justify>left</justify><ColumnWidthPDF></ColumnWidthPDF><ColumnWidthHTML></ColumnWidthHTML><column_title></column_title><tooltip></tooltip><group_header_label></group_header_label><group_header_label_xpos></group_header_label_xpos><group_header_data_xpos></group_header_data_xpos><group_trailer_label></group_trailer_label></Format></QueryColumn><QueryColumn><Name>lahir_tanggal</Name><TableName></TableName><ColumnName>lahir_tanggal</ColumnName><ColumnType>char</ColumnType><ColumnLength>30</ColumnLength><Format><column_display>hide</column_display><content_type>plain</content_type><ColumnStartPDF></ColumnStartPDF><justify>left</justify><ColumnWidthPDF></ColumnWidthPDF><ColumnWidthHTML></ColumnWidthHTML><column_title></column_title><tooltip></tooltip><group_header_label></group_header_label><group_header_label_xpos></group_header_label_xpos><group_header_data_xpos></group_header_data_xpos><group_trailer_label></group_trailer_label></Format></QueryColumn><QueryColumn><Name>pekerjaan</Name><TableName></TableName><ColumnName>pekerjaan</ColumnName><ColumnType>char</ColumnType><ColumnLength>30</ColumnLength><Format><column_display>hide</column_display><content_type>plain</content_type><ColumnStartPDF></ColumnStartPDF><justify>left</justify><ColumnWidthPDF></ColumnWidthPDF><ColumnWidthHTML></ColumnWidthHTML><column_title></column_title><tooltip></tooltip><group_header_label></group_header_label><group_header_label_xpos></group_header_label_xpos><group_header_data_xpos></group_header_data_xpos><group_trailer_label></group_trailer_label></Format></QueryColumn><QueryColumn><Name>alamat</Name><TableName></TableName><ColumnName>alamat</ColumnName><ColumnType>char</ColumnType><ColumnLength>30</ColumnLength><Format><column_display>hide</column_display><content_type>plain</content_type><ColumnStartPDF></ColumnStartPDF><justify>left</justify><ColumnWidthPDF></ColumnWidthPDF><ColumnWidthHTML></ColumnWidthHTML><column_title></column_title><tooltip></tooltip><group_header_label></group_header_label><group_header_label_xpos></group_header_label_xpos><group_header_data_xpos></group_header_data_xpos><group_trailer_label></group_trailer_label></Format></QueryColumn></QueryColumns><OrderColumns></OrderColumns><PreSQLS></PreSQLS></Query><Assignments></Assignments><Criteria></Criteria><Output><PageHeaders><PageHeader><LineNumber>1</LineNumber><HeaderText>{STYLE height:100px;background-image:images/header.png;}</HeaderText><Format><ColumnStartPDF></ColumnStartPDF><justify>center</justify><ColumnWidthPDF></ColumnWidthPDF><ShowInPDF>yes</ShowInPDF><ShowInHTML>no</ShowInHTML></Format></PageHeader><PageHeader><LineNumber>2</LineNumber><HeaderText>BERDASARKAN PERATURAN DAERAH KOTA BANDUNG NOMOR 11 TAHUN 2007 TENTANG MENDIRIKAN BANGUNAN{STYLE font-size:14pt;padding:70px 0px 0px 0px;}</HeaderText><Format><ColumnStartPDF></ColumnStartPDF><justify>center</justify><ColumnWidthPDF></ColumnWidthPDF><ShowInPDF>yes</ShowInPDF><ShowInHTML>no</ShowInHTML></Format></PageHeader><PageHeader><LineNumber>3</LineNumber><HeaderText>Diberikan izin mendirikan bangunan kepada:{STYLE padding:120px 0px 5px 20px;}</HeaderText><Format><ColumnStartPDF></ColumnStartPDF><justify>left</justify><ColumnWidthPDF></ColumnWidthPDF><ShowInPDF>yes</ShowInPDF><ShowInHTML>no</ShowInHTML></Format></PageHeader><PageHeader><LineNumber>4</LineNumber><HeaderText>Nama           : {nama}{STYLE padding:140px 0px 5px 30px;}</HeaderText><Format><ColumnStartPDF></ColumnStartPDF><justify>left</justify><ColumnWidthPDF></ColumnWidthPDF><ShowInPDF>yes</ShowInPDF><ShowInHTML>no</ShowInHTML></Format></PageHeader><PageHeader><LineNumber>5</LineNumber><HeaderText>No. KTP       : {no_ktp}{STYLE padding:150px 0px 5px 30px;}</HeaderText><Format><ColumnStartPDF></ColumnStartPDF><justify>left</justify><ColumnWidthPDF></ColumnWidthPDF><ShowInPDF>yes</ShowInPDF><ShowInHTML>no</ShowInHTML></Format></PageHeader><PageHeader><LineNumber>6</LineNumber><HeaderText>TTL              : {lahir_tempat}, {lahir_tanggal}{STYLE padding:160px 0px 5px 30px;}</HeaderText><Format><ColumnStartPDF></ColumnStartPDF><justify>left</justify><ColumnWidthPDF></ColumnWidthPDF><ShowInPDF>yes</ShowInPDF><ShowInHTML>no</ShowInHTML></Format></PageHeader><PageHeader><LineNumber>7</LineNumber><HeaderText>Pekerjaan     : {pekerjaan}{STYLE padding:170px 0px 5px 30px;}</HeaderText><Format><ColumnStartPDF></ColumnStartPDF><justify>left</justify><ColumnWidthPDF></ColumnWidthPDF><ShowInPDF>yes</ShowInPDF><ShowInHTML>no</ShowInHTML></Format></PageHeader><PageHeader><LineNumber>8</LineNumber><HeaderText>Alamat     : {alamat}{STYLE padding:180px 0px 5px 30px;}</HeaderText><Format><ColumnStartPDF></ColumnStartPDF><justify>left</justify><ColumnWidthPDF></ColumnWidthPDF><ShowInPDF>yes</ShowInPDF><ShowInHTML>no</ShowInHTML></Format></PageHeader></PageHeaders><PageFooters><PageFooter><LineNumber>2</LineNumber><FooterText>Page: {PAGE}{STYLE border-width: 1 0 0 0; margin: 40 0 0 0; font-style: italic; }</FooterText><Format><ColumnStartPDF></ColumnStartPDF><justify>center</justify><ColumnWidthPDF></ColumnWidthPDF><ShowInPDF>no</ShowInPDF><ShowInHTML>no</ShowInHTML></Format></PageFooter></PageFooters><DisplayOrders><DisplayOrder><ColumnName>no_ktp</ColumnName><OrderNumber>1</OrderNumber></DisplayOrder><DisplayOrder><ColumnName>nama</ColumnName><OrderNumber>2</OrderNumber></DisplayOrder><DisplayOrder><ColumnName>lahir_tempat</ColumnName><OrderNumber>3</OrderNumber></DisplayOrder><DisplayOrder><ColumnName>lahir_tanggal</ColumnName><OrderNumber>4</OrderNumber></DisplayOrder><DisplayOrder><ColumnName>pekerjaan</ColumnName><OrderNumber>5</OrderNumber></DisplayOrder><DisplayOrder><ColumnName>alamat</ColumnName><OrderNumber>6</OrderNumber></DisplayOrder></DisplayOrders><Groups></Groups><Graphs></Graphs></Output></EntryForm></ReportQuery></Report>